<?xml version="1.0" encoding="UTF-8"?>
<site>
   <feature id="org.eclipse.nebula.widgets.nattable.core.feature">
      <category name="nattable-core"/>
   </feature>
   <feature id="org.eclipse.nebula.widgets.nattable.extension.e4.feature">
      <category name="nattable-extensions"/>
   </feature>
   <feature id="org.eclipse.nebula.widgets.nattable.extension.glazedlists.feature">
      <category name="nattable-extensions"/>
   </feature>
   <feature id="org.eclipse.nebula.widgets.nattable.extension.nebula.feature">
      <category name="nattable-extensions"/>
   </feature>
   <feature id="org.eclipse.nebula.widgets.nattable.extension.poi.feature">
      <category name="nattable-extensions"/>
   </feature>
   <bundle id="org.eclipse.nebula.widgets.nattable.dataset">
      <category name="nattable-dataset"/>
   </bundle>
   <category-def name="nattable-core" label="NatTable Core">
      <description>
         The core NatTable functions.
      </description>
   </category-def>
   <category-def name="nattable-extensions" label="NatTable Extensions">
      <description>
         Extensions to provide additional features based on third-party libraries.
      </description>
   </category-def>
   <category-def name="nattable-dataset" label="NatTable DataSet">
      <description>
         NatTable example data used in examples.
      </description>
   </category-def>
</site>
